LICENSE
MANIFEST.in
README.md
setup.py
django_summernote_ajax/__init__.py
django_summernote_ajax/apps.py
django_summernote_ajax/forms.py
django_summernote_ajax/models.py
django_summernote_ajax/settings.py
django_summernote_ajax/tests.py
django_summernote_ajax/views.py
django_summernote_ajax/widgets.py
django_summernote_ajax.egg-info/PKG-INFO
django_summernote_ajax.egg-info/SOURCES.txt
django_summernote_ajax.egg-info/dependency_links.txt
django_summernote_ajax.egg-info/not-zip-safe
django_summernote_ajax.egg-info/requires.txt
django_summernote_ajax.egg-info/top_level.txt
django_summernote_ajax/migrations/__init__.py
django_summernote_ajax/migrations/__pycache__/__init__.cpython-36.pyc
django_summernote_ajax/static/css/summernote/summernote-bs4.css
django_summernote_ajax/static/css/summernote/summernote-lite.css
django_summernote_ajax/static/css/summernote/summernote.css
django_summernote_ajax/static/css/summernote/font/summernote.eot
django_summernote_ajax/static/css/summernote/font/summernote.ttf
django_summernote_ajax/static/css/summernote/font/summernote.woff
django_summernote_ajax/static/js/summernote/csrf-cookie.js
django_summernote_ajax/static/js/summernote/summernote-bs4.js
django_summernote_ajax/static/js/summernote/summernote-bs4.min.js
django_summernote_ajax/static/js/summernote/summernote-lite.js
django_summernote_ajax/static/js/summernote/summernote.js
django_summernote_ajax/static/js/summernote/summernote.min.js
django_summernote_ajax/templates/django_summernote_ajax/django_summernote_ajax.html
sandbox_app/__init__.py
sandbox_app/admin.py
sandbox_app/apps.py
sandbox_app/forms.py
sandbox_app/models.py
sandbox_app/settings.py
sandbox_app/tasks.py
sandbox_app/tests.py
sandbox_app/viewmixins.py
sandbox_app/views.py
sandbox_app/widgets.py
sandbox_app/migrations/0001_initial.py
sandbox_app/migrations/__init__.py