Metadata-Version: 1.1
Name: django-summernote-ajax
Version: 0.0.0.2
Summary: Yet another Summernote plugin for Django
Home-page: http://github.com/summernote/django-summernote-ajax
Author: django-summernote-ajax maintainers
Author-email: UNKNOWN
License: MIT
Keywords: Django,Summernote,jQuery
Platform: UNKNOWN
Classifier: Development Status :: 3 - Alpha
Classifier: Intended Audience :: Developers
Classifier: Topic :: Software Development :: Build Tools
Classifier: License :: OSI Approved :: MIT License
Classifier: Framework :: Django :: 1.8
Classifier: Framework :: Django :: 1.11
Classifier: Framework :: Django :: 2.0
Classifier: Programming Language :: Python :: 3
Classifier: Programming Language :: Python :: 3.4
Classifier: Programming Language :: Python :: 3.5
Classifier: Programming Language :: Python :: 3.6
